<?xml version="1.0" encoding="utf-8"?>
<IncrementalBankBuild Version="6" Flags="1324483096">
	<Platform GUID="{10E0EAF6-86D2-44E2-AA15-810E2D998A81}">
		<Banks>
			<Language ID="393239870">
				<File Name="ESD_Main_SoundBank" Hash="3499782732" Timestamp="1526731275"/>
				<File Name="Init" Hash="4148972090" Timestamp="1527848021"/>
			</Language>
			<Language ID="684519430">
				<File Name="ESD_Main_SoundBank" Hash="262006326" Timestamp="1527869572"/>
			</Language>
		</Banks>
		<XMLInfo>
			<Language ID="393239870">
				<File Name="ESD_Main_SoundBank" Hash="1161936728" Timestamp="1526731275"/>
				<File Name="Init" Hash="1176128004" Timestamp="1527848021"/>
			</Language>
			<Language ID="684519430">
				<File Name="ESD_Main_SoundBank" Hash="1855211983" Timestamp="1527869572"/>
			</Language>
			<Language ID="-1">
				<File Name="" Hash="1356759541" Timestamp="1527869572"/>
			</Language>
		</XMLInfo>
		<JSONInfo>
			<Language ID="393239870">
				<File Name="ESD_Main_SoundBank" Hash="2020150458" Timestamp="1526731275"/>
				<File Name="Init" Hash="2699387357" Timestamp="1527848021"/>
			</Language>
			<Language ID="684519430">
				<File Name="ESD_Main_SoundBank" Hash="1804124165" Timestamp="1527869572"/>
			</Language>
			<Language ID="-1">
				<File Name="" Hash="2358163083" Timestamp="1527869572"/>
			</Language>
		</JSONInfo>
	</Platform>
</IncrementalBankBuild>
